[
  {
    "id": "92f62f2e-da2f-407f-b074-3f105ea17b78",
    "name": "Jonas K.",
    "stars": 5,
    "message": "Die Plattform funktioniert zuverlässig, transparent und ohne versteckte Kosten. Ich finde schnell Talente, die wirklich helfen — und gleichzeitig unterstützt jede Buchung soziale Projekte. Das ist modernes, verantwortungsvolles Buchen.“",
    "date": "7.6.2026",
    "submitted_at": "2026-06-07T11:12:14.956Z"
  },
  {
    "id": "b03e1ec7-48f5-4562-9a4a-6d0ac364267e",
    "name": "Jonas K.",
    "stars": 5,
    "message": "Die Plattform funktioniert zuverlässig, transparent und ohne versteckte Kosten. Ich finde schnell Talente, die wirklich helfen — und gleichzeitig unterstützt jede Buchung soziale Projekte. Das ist modernes, verantwortungsvolles Buchen.",
    "date": "7.6.2026",
    "submitted_at": "2026-06-07T11:15:49.724Z"
  }
]